conserve/__init__.py
conserve/conserve_agent.py
conserve/utils.py
conserve-0.1.1.dist-info/LICENSE
conserve-0.1.1.dist-info/METADATA
conserve-0.1.1.dist-info/WHEEL
conserve-0.1.1.dist-info/top_level.txt
conserve-0.1.1.dist-info/RECORD
